gsd_lite/__init__.py
gsd_lite/__main__.py
gsd_lite/template/AGENTS.md
gsd_lite/template/ARCHITECTURE.md
gsd_lite/template/HISTORY.md
gsd_lite/template/INBOX.md
gsd_lite/template/PROJECT.md
gsd_lite/template/PROTOCOL.md
gsd_lite/template/VERSION
gsd_lite/template/WORK.md
gsd_lite/template/workflows/checkpoint.md
gsd_lite/template/workflows/execution.md
gsd_lite/template/workflows/housekeeping.md
gsd_lite/template/workflows/map-codebase.md
gsd_lite/template/workflows/moodboard.md
gsd_lite/template/workflows/new-project.md
gsd_lite/template/workflows/progress.md
gsd_lite/template/workflows/whiteboard.md
gsd_lite-1.10.0.dist-info/METADATA
gsd_lite-1.10.0.dist-info/WHEEL
gsd_lite-1.10.0.dist-info/entry_points.txt
gsd_lite-1.10.0.dist-info/licenses/LICENSE
gsd_lite-1.10.0.dist-info/RECORD
