Metadata-Version: 2.4
Name: gsd-lite
Version: 1.10.0
Summary: A minimal protocol for Getting Things Done with AI agents
License-File: LICENSE
Requires-Python: >=3.9
Requires-Dist: rich>=13.0.0
Requires-Dist: typer>=0.9.0
